[
    {"japaneseK":"人 (1)","japaneseA":"ひと","japaneseR":"hito", "traduction":"humain"},
    {"japaneseK":"人 (2)","japaneseA":"じん","japaneseR":"jin", "traduction":"homme"},
    {"japaneseK":"人 (3)","japaneseA":"にん","japaneseR":"nin", "traduction":"personne"},
    {"japaneseK":"一 (1)","japaneseA":"いち","japaneseR":"ichi", "traduction":"un"},
    {"japaneseK":"一 (2)","japaneseA":"いつ","japaneseR":"itsu", "traduction":"un"},
    {"japaneseK":"七 (1)","japaneseA":"なな","japaneseR":"nana", "traduction":"sept"},
    {"japaneseK":"七 (2)","japaneseA":"しち","japaneseR":"shichi", "traduction":"sept"},
    {"japaneseK":"十 (1)","japaneseA":"じゅう","japaneseR":"jū", "traduction":"dix"},
    {"japaneseK":"十 (2)","japaneseA":"とお","japaneseR":"tō", "traduction":"dix"},
    {"japaneseK":"百","japaneseA":"ひゃく","japaneseR":"hyaku", "traduction":"cent"},
    {"japaneseK":"二 (1)","japaneseA":"に","japaneseR":"ni", "traduction":"deux"},
    {"japaneseK":"二 (2)","japaneseA":"じ","japaneseR":"ji", "traduction":"deux"},
    {"japaneseK":"三 (1)","japaneseA":"さん","japaneseR":"san", "traduction":"trois"},
    {"japaneseK":"三 (2)","japaneseA":"ぞう","japaneseR":"zō", "traduction":"trois"},
    {"japaneseK":"四 (1)","japaneseA":"し","japaneseR":"shi", "traduction":"quatre"},
    {"japaneseK":"四 (2)","japaneseA":"よん","japaneseR":"yon", "traduction":"quatre"},
    {"japaneseK":"五 (1)","japaneseA":"ご","japaneseR":"go", "traduction":"cinq"},
    {"japaneseK":"五 (2)","japaneseA":"いつつ","japaneseR":"itsutsu", "traduction":"cinq"},
    {"japaneseK":"六 (1)","japaneseA":"ろく","japaneseR":"roku", "traduction":"six"},
    {"japaneseK":"六 (2)","japaneseA":"む","japaneseR":"mu", "traduction":"six"},
    {"japaneseK":"八 (1)","japaneseA":"はち","japaneseR":"hachi", "traduction":"huit"},
    {"japaneseK":"八 (2)","japaneseA":"や","japaneseR":"ya", "traduction":"huit"},
    {"japaneseK":"九 (1)","japaneseA":"きゅう","japaneseR":"kyū", "traduction":"neuf"},
    {"japaneseK":"九 (2)","japaneseA":"く","japaneseR":"ku", "traduction":"neuf"},
    {"japaneseK":"二十","japaneseA":"にじゅう","japaneseR":"nijū", "traduction":"vingt"},
    {"japaneseK":"百五","japaneseA":"ひゃくご","japaneseR":"hyakugo", "traduction":"cent cinq"},
    {"japaneseK":"千二百","japaneseA":"せんにひゃく","japaneseR":"sennihyaku", "traduction":"mille deux cents"},
    {"japaneseK":"日本","japaneseA":"にほん","japaneseR":"nihon", "traduction":"Japon"},
    {"japaneseK":"東京","japaneseA":"とうきょう","japaneseR":"Tōkyō", "traduction":"Tokyo"},
    {"japaneseK":"京都","japaneseA":"きょうと","japaneseR":"Kyōto", "traduction":"Kyoto"},
    {"japaneseK":"大学","japaneseA":"だいがく","japaneseR":"daigaku", "traduction":"université"},
    {"japaneseK":"食べる","japaneseA":"たべる","japaneseR":"taberu", "traduction":"manger"},
    {"japaneseK":"飲む","japaneseA":"のむ","japaneseR":"nomu", "traduction":"boire"},
    {"japaneseK":"行く","japaneseA":"いく","japaneseR":"iku", "traduction":"aller"},
    {"japaneseK":"来る","japaneseA":"くる","japaneseR":"kuru", "traduction":"venir"},
    {"japaneseK":"見る","japaneseA":"みる","japaneseR":"miru", "traduction":"voir"},
    {"japaneseK":"聞く","japaneseA":"きく","japaneseR":"kiku", "traduction":"écouter"},
    {"japaneseK":"話す","japaneseA":"はなす","japaneseR":"hanasu", "traduction":"parler"},
    {"japaneseK":"書く","japaneseA":"かく","japaneseR":"kaku", "traduction":"écrire"},
    {"japaneseK":"千","japaneseA":"せん","japaneseR":"sen", "traduction":"mille"},
    {"japaneseK":"日 (1)","japaneseA":"にち","japaneseR":"nichi", "traduction":"jour"},
    {"japaneseK":"日 (2)","japaneseA":"じつ","japaneseR":"jitsu", "traduction":"jour"},
    {"japaneseK":"月","japaneseA":"つき","japaneseR":"tsuki", "traduction":"lune"},
    {"japaneseK":"火","japaneseA":"ひ","japaneseR":"hi", "traduction":"feu"},
    {"japaneseK":"水","japaneseA":"みず","japaneseR":"mizu", "traduction":"eau"},
    {"japaneseK":"木","japaneseA":"き","japaneseR":"ki", "traduction":"arbre"},
    {"japaneseK":"金","japaneseA":"きん","japaneseR":"kin", "traduction":"or"},
    {"japaneseK":"土","japaneseA":"つち","japaneseR":"tsuchi", "traduction":"terre"},
    {"japaneseK":"空 (1)","japaneseA":"そら","japaneseR":"sora", "traduction":"ciel"},
    {"japaneseK":"空 (2)","japaneseA":"くう","japaneseR":"kū", "traduction":"vide"},
    {"japaneseK":"風","japaneseA":"かぜ","japaneseR":"kaze", "traduction":"vent"},
    {"japaneseK":"雨","japaneseA":"あめ","japaneseR":"ame", "traduction":"pluie"},
    {"japaneseK":"雪","japaneseA":"ゆき","japaneseR":"yuki", "traduction":"neige"},
    {"japaneseK":"花","japaneseA":"はな","japaneseR":"hana", "traduction":"fleur"},
    {"japaneseK":"鳥","japaneseA":"とり","japaneseR":"tori", "traduction":"oiseau"},
    {"japaneseK":"魚","japaneseA":"さかな","japaneseR":"sakana", "traduction":"poisson"},
    {"japaneseK":"犬","japaneseA":"いぬ","japaneseR":"inu", "traduction":"chien"},
    {"japaneseK":"猫","japaneseA":"ねこ","japaneseR":"neko", "traduction":"chat"},
    {"japaneseK":"家","japaneseA":"いえ","japaneseR":"ie", "traduction":"maison"},
    {"japaneseK":"学校","japaneseA":"がっこう","japaneseR":"gakkō", "traduction":"école"}
]
